rtl/v45/ifa_relation_frame.sv
`timescale 1ns/1ps

// ============================================================================
// IFÁ Processor V4.5
// Native Relation Frame Register
// ============================================================================
//
// Purpose:
//   Stores one complete IFÁ relation frame produced by a YÀRÁ processing
//   element.
//
// Architecture:
//   Binary operands
//       ↓
//   Φ-P8
//       ↓
//   Relation operation
//       ↓
//   RelationFrame register
//       ↓
//   Relation Memory Unit
//
// This module intentionally performs no arithmetic or relation computation.
// It is a synchronous storage boundary equivalent to the Python
// RelationFrame dataclass.
// ============================================================================

module ifa_relation_frame #(
    parameter int WIDTH         = 8,
    parameter int REL_ID_WIDTH  = 8,
    parameter int OP_WIDTH      = 4,
    parameter int VALUE_WIDTH   = WIDTH + 1
) (
    input  logic                     clk,
    input  logic                     rst_n,
    input  logic                     load_i,

    // ------------------------------------------------------------------------
    // Incoming frame identity
    // ------------------------------------------------------------------------
    input  logic [REL_ID_WIDTH-1:0]  relation_id_i,
    input  logic [OP_WIDTH-1:0]      operation_i,

    // ------------------------------------------------------------------------
    // Incoming resolved operands
    // ------------------------------------------------------------------------
    input  logic [WIDTH-1:0]         operand_a_i,
    input  logic [WIDTH-1:0]         operand_b_i,

    // ------------------------------------------------------------------------
    // Incoming Φ-P8 channels
    // ------------------------------------------------------------------------
    input  logic [WIDTH-1:0]         phi_a_i,
    input  logic [WIDTH-1:0]         phi_b_i,
    input  logic [WIDTH-1:0]         phi_y_i,

    // ------------------------------------------------------------------------
    // Incoming result and relation channels
    // ------------------------------------------------------------------------
    input  logic [WIDTH-1:0]         y_i,
    input  logic [WIDTH-1:0]         ra_i,
    input  logic [WIDTH-1:0]         rd_i,
    input  logic [WIDTH-1:0]         r0_i,

    // Full unrestricted result.
    //
    // WIDTH+1 supports one-bit arithmetic transport for the first RTL stage.
    // Larger multiplication support will later use a configurable value width.
    input  logic [VALUE_WIDTH-1:0]   value_i,

    // ------------------------------------------------------------------------
    // Incoming state channels
    // ------------------------------------------------------------------------
    input  logic                     transport_i,
    input  logic                     eq_i,
    input  logic                     gt_i,
    input  logic                     lt_i,
    input  logic                     state_i,
    input  logic                     valid_i,

    // ------------------------------------------------------------------------
    // Stored frame identity
    // ------------------------------------------------------------------------
    output logic [REL_ID_WIDTH-1:0]  relation_id_o,
    output logic [OP_WIDTH-1:0]      operation_o,

    // ------------------------------------------------------------------------
    // Stored operands
    // ------------------------------------------------------------------------
    output logic [WIDTH-1:0]         operand_a_o,
    output logic [WIDTH-1:0]         operand_b_o,

    // ------------------------------------------------------------------------
    // Stored Φ-P8 channels
    // ------------------------------------------------------------------------
    output logic [WIDTH-1:0]         phi_a_o,
    output logic [WIDTH-1:0]         phi_b_o,
    output logic [WIDTH-1:0]         phi_y_o,

    // ------------------------------------------------------------------------
    // Stored result and relation channels
    // ------------------------------------------------------------------------
    output logic [WIDTH-1:0]         y_o,
    output logic [WIDTH-1:0]         ra_o,
    output logic [WIDTH-1:0]         rd_o,
    output logic [WIDTH-1:0]         r0_o,
    output logic [VALUE_WIDTH-1:0]   value_o,

    // ------------------------------------------------------------------------
    // Stored state channels
    // ------------------------------------------------------------------------
    output logic                     transport_o,
    output logic                     eq_o,
    output logic                     gt_o,
    output logic                     lt_o,
    output logic                     state_o,
    output logic                     valid_o
);

    // ------------------------------------------------------------------------
    // Synchronous frame storage
    // ------------------------------------------------------------------------
    always_ff @(posedge clk or negedge rst_n) begin
        if (!rst_n) begin
            relation_id_o <= '0;
            operation_o   <= '0;

            operand_a_o   <= '0;
            operand_b_o   <= '0;

            phi_a_o       <= '0;
            phi_b_o       <= '0;
            phi_y_o       <= '0;

            y_o           <= '0;
            ra_o          <= '0;
            rd_o          <= '0;
            r0_o          <= '0;
            value_o       <= '0;

            transport_o   <= 1'b0;
            eq_o          <= 1'b0;
            gt_o          <= 1'b0;
            lt_o          <= 1'b0;
            state_o       <= 1'b0;
            valid_o       <= 1'b0;
        end
        else if (load_i) begin
            relation_id_o <= relation_id_i;
            operation_o   <= operation_i;

            operand_a_o   <= operand_a_i;
            operand_b_o   <= operand_b_i;

            phi_a_o       <= phi_a_i;
            phi_b_o       <= phi_b_i;
            phi_y_o       <= phi_y_i;

            y_o           <= y_i;
            ra_o          <= ra_i;
            rd_o          <= rd_i;
            r0_o          <= r0_i;
            value_o       <= value_i;

            transport_o   <= transport_i;
            eq_o          <= eq_i;
            gt_o          <= gt_i;
            lt_o          <= lt_i;
            state_o       <= state_i;
            valid_o       <= valid_i;
        end
    end

endmodule

tb/v45/tb_ifa_relation_frame.sv
`timescale 1ns/1ps

module tb_ifa_relation_frame;

    localparam int WIDTH        = 8;
    localparam int REL_ID_WIDTH = 8;
    localparam int OP_WIDTH     = 4;

    logic clk;
    logic rst_n;
    logic load_i;

    logic [REL_ID_WIDTH-1:0] relation_id_i;
    logic [OP_WIDTH-1:0]     operation_i;

    logic [WIDTH-1:0] operand_a_i;
    logic [WIDTH-1:0] operand_b_i;

    logic [WIDTH-1:0] phi_a_i;
    logic [WIDTH-1:0] phi_b_i;
    logic [WIDTH-1:0] phi_y_i;

    logic [WIDTH-1:0] y_i;
    logic [WIDTH-1:0] ra_i;
    logic [WIDTH-1:0] rd_i;
    logic [WIDTH-1:0] r0_i;
    logic [WIDTH:0]   value_i;

    logic transport_i;
    logic eq_i;
    logic gt_i;
    logic lt_i;
    logic state_i;
    logic valid_i;

    logic [REL_ID_WIDTH-1:0] relation_id_o;
    logic [OP_WIDTH-1:0]     operation_o;

    logic [WIDTH-1:0] operand_a_o;
    logic [WIDTH-1:0] operand_b_o;

    logic [WIDTH-1:0] phi_a_o;
    logic [WIDTH-1:0] phi_b_o;
    logic [WIDTH-1:0] phi_y_o;

    logic [WIDTH-1:0] y_o;
    logic [WIDTH-1:0] ra_o;
    logic [WIDTH-1:0] rd_o;
    logic [WIDTH-1:0] r0_o;
    logic [WIDTH:0]   value_o;

    logic transport_o;
    logic eq_o;
    logic gt_o;
    logic lt_o;
    logic state_o;
    logic valid_o;

    int tests_run;
    int tests_failed;

    ifa_relation_frame #(
        .WIDTH        (WIDTH),
        .REL_ID_WIDTH (REL_ID_WIDTH),
        .OP_WIDTH     (OP_WIDTH)
    ) dut (
        .clk           (clk),
        .rst_n         (rst_n),
        .load_i        (load_i),

        .relation_id_i (relation_id_i),
        .operation_i   (operation_i),

        .operand_a_i   (operand_a_i),
        .operand_b_i   (operand_b_i),

        .phi_a_i       (phi_a_i),
        .phi_b_i       (phi_b_i),
        .phi_y_i       (phi_y_i),

        .y_i           (y_i),
        .ra_i          (ra_i),
        .rd_i          (rd_i),
        .r0_i          (r0_i),
        .value_i       (value_i),

        .transport_i   (transport_i),
        .eq_i          (eq_i),
        .gt_i          (gt_i),
        .lt_i          (lt_i),
        .state_i       (state_i),
        .valid_i       (valid_i),

        .relation_id_o (relation_id_o),
        .operation_o   (operation_o),

        .operand_a_o   (operand_a_o),
        .operand_b_o   (operand_b_o),

        .phi_a_o       (phi_a_o),
        .phi_b_o       (phi_b_o),
        .phi_y_o       (phi_y_o),

        .y_o           (y_o),
        .ra_o          (ra_o),
        .rd_o          (rd_o),
        .r0_o          (r0_o),
        .value_o       (value_o),

        .transport_o   (transport_o),
        .eq_o          (eq_o),
        .gt_o          (gt_o),
        .lt_o          (lt_o),
        .state_o       (state_o),
        .valid_o       (valid_o)
    );

    // 100 MHz clock.
    initial clk = 1'b0;
    always #5 clk = ~clk;

    task automatic expect_bit(
        input string name,
        input logic actual,
        input logic expected
    );
        begin
            tests_run++;

            if (actual !== expected) begin
                tests_failed++;

                $display(
                    "FAIL: %-18s actual=%b expected=%b",
                    name,
                    actual,
                    expected
                );
            end
            else begin
                $display(
                    "PASS: %-18s value=%b",
                    name,
                    actual
                );
            end
        end
    endtask

    task automatic expect_value(
        input string name,
        input logic [31:0] actual,
        input logic [31:0] expected
    );
        begin
            tests_run++;

            if (actual !== expected) begin
                tests_failed++;

                $display(
                    "FAIL: %-18s actual=0x%0h expected=0x%0h",
                    name,
                    actual,
                    expected
                );
            end
            else begin
                $display(
                    "PASS: %-18s value=0x%0h",
                    name,
                    actual
                );
            end
        end
    endtask

    task automatic clear_inputs;
        begin
            load_i        = 1'b0;

            relation_id_i = '0;
            operation_i   = '0;

            operand_a_i   = '0;
            operand_b_i   = '0;

            phi_a_i       = '0;
            phi_b_i       = '0;
            phi_y_i       = '0;

            y_i           = '0;
            ra_i          = '0;
            rd_i          = '0;
            r0_i          = '0;
            value_i       = '0;

            transport_i   = 1'b0;
            eq_i          = 1'b0;
            gt_i          = 1'b0;
            lt_i          = 1'b0;
            state_i       = 1'b0;
            valid_i       = 1'b0;
        end
    endtask

    task automatic check_reset_state;
        begin
            expect_value("reset relation_id", relation_id_o, 0);
            expect_value("reset operation",   operation_o,   0);

            expect_value("reset operand_a", operand_a_o, 0);
            expect_value("reset operand_b", operand_b_o, 0);

            expect_value("reset phi_a", phi_a_o, 0);
            expect_value("reset phi_b", phi_b_o, 0);
            expect_value("reset phi_y", phi_y_o, 0);

            expect_value("reset y",     y_o,     0);
            expect_value("reset ra",    ra_o,    0);
            expect_value("reset rd",    rd_o,    0);
            expect_value("reset r0",    r0_o,    0);
            expect_value("reset value", value_o, 0);

            expect_bit("reset transport", transport_o, 0);
            expect_bit("reset eq",        eq_o,        0);
            expect_bit("reset gt",        gt_o,        0);
            expect_bit("reset lt",        lt_o,        0);
            expect_bit("reset state",     state_o,     0);
            expect_bit("reset valid",     valid_o,     0);
        end
    endtask

    initial begin
        $dumpfile("sim_v45/ifa_relation_frame.vcd");
        $dumpvars(0, tb_ifa_relation_frame);

        tests_run    = 0;
        tests_failed = 0;

        clear_inputs();

        // --------------------------------------------------------------------
        // Test 1: asynchronous reset
        // --------------------------------------------------------------------
        rst_n = 1'b0;
        #2;

        check_reset_state();

        repeat (2) @(posedge clk);
        rst_n = 1'b1;

        // --------------------------------------------------------------------
        // Test 2: load R0 = PAPO 2 ATI 3
        //
        // Expected relation channels:
        //   Y  = 5
        //   RA = 2 & 3       = 2
        //   RD = 2 ^ 3       = 1
        //   R0 = ~(2 | 3)    = FC
        // --------------------------------------------------------------------
        @(negedge clk);

        load_i        = 1'b1;

        relation_id_i = 8'h00;
        operation_i   = 4'h0;

        operand_a_i   = 8'h02;
        operand_b_i   = 8'h03;

        // Values taken from the currently verified Φ-P8 software backend.
        // The storage register does not reinterpret these values.
        phi_a_i       = 8'hA2;
        phi_b_i       = 8'hA3;
        phi_y_i       = 8'hA5;

        y_i           = 8'h05;
        ra_i          = 8'h02;
        rd_i          = 8'h01;
        r0_i          = 8'hFC;
        value_i       = 9'h005;

        transport_i   = 1'b0;
        eq_i          = 1'b0;
        gt_i          = 1'b0;
        lt_i          = 1'b1;
        state_i       = 1'b0;
        valid_i       = 1'b1;

        @(posedge clk);
        #1;

        expect_value("R0 relation_id", relation_id_o, 8'h00);
        expect_value("R0 operation",   operation_o,   4'h0);

        expect_value("R0 operand_a", operand_a_o, 8'h02);
        expect_value("R0 operand_b", operand_b_o, 8'h03);

        expect_value("R0 phi_a", phi_a_o, 8'hA2);
        expect_value("R0 phi_b", phi_b_o, 8'hA3);
        expect_value("R0 phi_y", phi_y_o, 8'hA5);

        expect_value("R0 y",     y_o,     8'h05);
        expect_value("R0 ra",    ra_o,    8'h02);
        expect_value("R0 rd",    rd_o,    8'h01);
        expect_value("R0 r0",    r0_o,    8'hFC);
        expect_value("R0 value", value_o, 9'h005);

        expect_bit("R0 transport", transport_o, 1'b0);
        expect_bit("R0 eq",        eq_o,        1'b0);
        expect_bit("R0 gt",        gt_o,        1'b0);
        expect_bit("R0 lt",        lt_o,        1'b1);
        expect_bit("R0 state",     state_o,     1'b0);
        expect_bit("R0 valid",     valid_o,     1'b1);

        // --------------------------------------------------------------------
        // Test 3: load disabled; existing frame must remain unchanged
        // --------------------------------------------------------------------
        @(negedge clk);

        load_i        = 1'b0;
        relation_id_i = 8'h55;
        y_i           = 8'hFF;
        valid_i       = 1'b0;

        @(posedge clk);
        #1;

        expect_value("hold relation_id", relation_id_o, 8'h00);
        expect_value("hold y",           y_o,           8'h05);
        expect_bit  ("hold valid",       valid_o,       1'b1);

        // --------------------------------------------------------------------
        // Test 4: load transported frame
        //
        // Mirrors:
        //   R5 = 11 DAGBA 28 = 308
        //   Y  = 308 mod 256 = 52 = 0x34
        //   T  = 1
        // --------------------------------------------------------------------
        @(negedge clk);

        load_i        = 1'b1;

        relation_id_i = 8'h05;
        operation_i   = 4'h2;

        operand_a_i   = 8'h0B;
        operand_b_i   = 8'h1C;

        phi_a_i       = 8'hAB;
        phi_b_i       = 8'hBC;
        phi_y_i       = 8'hB4;

        y_i           = 8'h34;
        ra_i          = 8'h08;
        rd_i          = 8'h17;
        r0_i          = 8'hE0;
        value_i       = 9'h134;

        transport_i   = 1'b1;
        eq_i          = 1'b0;
        gt_i          = 1'b0;
        lt_i          = 1'b1;
        state_i       = 1'b1;
        valid_i       = 1'b1;

        @(posedge clk);
        #1;

        expect_value("R5 relation_id", relation_id_o, 8'h05);
        expect_value("R5 operation",   operation_o,   4'h2);

        expect_value("R5 operand_a", operand_a_o, 8'h0B);
        expect_value("R5 operand_b", operand_b_o, 8'h1C);

        expect_value("R5 y",     y_o,     8'h34);
        expect_value("R5 ra",    ra_o,    8'h08);
        expect_value("R5 rd",    rd_o,    8'h17);
        expect_value("R5 r0",    r0_o,    8'hE0);
        expect_value("R5 value", value_o, 9'h134);

        expect_bit("R5 transport", transport_o, 1'b1);
        expect_bit("R5 state",     state_o,     1'b1);
        expect_bit("R5 valid",     valid_o,     1'b1);

        // Relation partition validation for the stored R5 frame.
        expect_value(
            "partition complete",
            ra_o | rd_o | r0_o,
            8'hFF
        );

        expect_value(
            "RA/RD disjoint",
            ra_o & rd_o,
            8'h00
        );

        expect_value(
            "RA/R0 disjoint",
            ra_o & r0_o,
            8'h00
        );

        expect_value(
            "RD/R0 disjoint",
            rd_o & r0_o,
            8'h00
        );

        // --------------------------------------------------------------------
        // Test 5: reset after populated frame
        // --------------------------------------------------------------------
        #2;
        rst_n = 1'b0;
        #1;

        check_reset_state();

        // --------------------------------------------------------------------
        // Final result
        // --------------------------------------------------------------------
        $display("");
        $display("============================================================");
        $display("IFÁ V4.5 RELATION FRAME RTL TEST SUMMARY");
        $display("============================================================");
        $display("Tests run    : %0d", tests_run);
        $display("Tests failed : %0d", tests_failed);

        if (tests_failed == 0) begin
            $display("RESULT       : PASS");
            $display("RelationFrame RTL storage behaviour verified.");
        end
        else begin
            $display("RESULT       : FAIL");
            $fatal(
                1,
                "%0d RelationFrame tests failed.",
                tests_failed
            );
        end

        $finish;
    end

endmodule

sim_v45/ifa_relation_frame.vcd
$date
	Sat Jul 18 13:53:17 2026
$end
$version
	Icarus Verilog
$end
$timescale
	1ps
$end
$scope module tb_ifa_relation_frame $end
$var wire 8 ! y_o [7:0] $end
$var wire 9 " value_o [8:0] $end
$var wire 1 # valid_o $end
$var wire 1 $ transport_o $end
$var wire 1 % state_o $end
$var wire 8 & relation_id_o [7:0] $end
$var wire 8 ' rd_o [7:0] $end
$var wire 8 ( ra_o [7:0] $end
$var wire 8 ) r0_o [7:0] $end
$var wire 8 * phi_y_o [7:0] $end
$var wire 8 + phi_b_o [7:0] $end
$var wire 8 , phi_a_o [7:0] $end
$var wire 4 - operation_o [3:0] $end
$var wire 8 . operand_b_o [7:0] $end
$var wire 8 / operand_a_o [7:0] $end
$var wire 1 0 lt_o $end
$var wire 1 1 gt_o $end
$var wire 1 2 eq_o $end
$var parameter 32 3 OP_WIDTH $end
$var parameter 32 4 REL_ID_WIDTH $end
$var parameter 32 5 WIDTH $end
$var reg 1 6 clk $end
$var reg 1 7 eq_i $end
$var reg 1 8 gt_i $end
$var reg 1 9 load_i $end
$var reg 1 : lt_i $end
$var reg 8 ; operand_a_i [7:0] $end
$var reg 8 < operand_b_i [7:0] $end
$var reg 4 = operation_i [3:0] $end
$var reg 8 > phi_a_i [7:0] $end
$var reg 8 ? phi_b_i [7:0] $end
$var reg 8 @ phi_y_i [7:0] $end
$var reg 8 A r0_i [7:0] $end
$var reg 8 B ra_i [7:0] $end
$var reg 8 C rd_i [7:0] $end
$var reg 8 D relation_id_i [7:0] $end
$var reg 1 E rst_n $end
$var reg 1 F state_i $end
$var reg 1 G transport_i $end
$var reg 1 H valid_i $end
$var reg 9 I value_i [8:0] $end
$var reg 8 J y_i [7:0] $end
$var integer 32 K tests_failed [31:0] $end
$var integer 32 L tests_run [31:0] $end
$scope module dut $end
$var wire 1 6 clk $end
$var wire 1 7 eq_i $end
$var wire 1 8 gt_i $end
$var wire 1 9 load_i $end
$var wire 1 : lt_i $end
$var wire 8 M operand_a_i [7:0] $end
$var wire 8 N operand_b_i [7:0] $end
$var wire 4 O operation_i [3:0] $end
$var wire 8 P phi_a_i [7:0] $end
$var wire 8 Q phi_b_i [7:0] $end
$var wire 8 R phi_y_i [7:0] $end
$var wire 8 S r0_i [7:0] $end
$var wire 8 T ra_i [7:0] $end
$var wire 8 U rd_i [7:0] $end
$var wire 8 V relation_id_i [7:0] $end
$var wire 1 E rst_n $end
$var wire 1 F state_i $end
$var wire 1 G transport_i $end
$var wire 1 H valid_i $end
$var wire 9 W value_i [8:0] $end
$var wire 8 X y_i [7:0] $end
$var parameter 32 Y OP_WIDTH $end
$var parameter 32 Z REL_ID_WIDTH $end
$var parameter 32 [ VALUE_WIDTH $end
$var parameter 32 \ WIDTH $end
$var reg 1 2 eq_o $end
$var reg 1 1 gt_o $end
$var reg 1 0 lt_o $end
$var reg 8 ] operand_a_o [7:0] $end
$var reg 8 ^ operand_b_o [7:0] $end
$var reg 4 _ operation_o [3:0] $end
$var reg 8 ` phi_a_o [7:0] $end
$var reg 8 a phi_b_o [7:0] $end
$var reg 8 b phi_y_o [7:0] $end
$var reg 8 c r0_o [7:0] $end
$var reg 8 d ra_o [7:0] $end
$var reg 8 e rd_o [7:0] $end
$var reg 8 f relation_id_o [7:0] $end
$var reg 1 % state_o $end
$var reg 1 $ transport_o $end
$var reg 1 # valid_o $end
$var reg 9 g value_o [8:0] $end
$var reg 8 h y_o [7:0] $end
$upscope $end
$scope task check_reset_state $end
$upscope $end
$scope task clear_inputs $end
$upscope $end
$scope task expect_bit $end
$upscope $end
$scope task expect_value $end
$upscope $end
$upscope $end
$enddefinitions $end
$comment Show the parameter values. $end
$dumpall
b1000 \
b1001 [
b1000 Z
b100 Y
b1000 5
b1000 4
b100 3
$end
#0
$dumpvars
b0 h
b0 g
b0 f
b0 e
b0 d
b0 c
b0 b
b0 a
b0 `
b0 _
b0 ^
b0 ]
b0 X
b0 W
b0 V
b0 U
b0 T
b0 S
b0 R
b0 Q
b0 P
b0 O
b0 N
b0 M
b0 L
b0 K
b0 J
b0 I
0H
0G
0F
0E
b0 D
b0 C
b0 B
b0 A
b0 @
b0 ?
b0 >
b0 =
b0 <
b0 ;
0:
09
08
07
06
02
01
00
b0 /
b0 .
b0 -
b0 ,
b0 +
b0 *
b0 )
b0 (
b0 '
b0 &
0%
0$
0#
b0 "
b0 !
$end
#2000
b10010 L
#5000
16
#10000
06
#15000
1E
16
#20000
1H
1:
b101 I
b101 W
b11111100 A
b11111100 S
b1 C
b1 U
b10 B
b10 T
b101 J
b101 X
b10100101 @
b10100101 R
b10100011 ?
b10100011 Q
b10100010 >
b10100010 P
b11 <
b11 N
b10 ;
b10 M
19
06
#25000
1#
10
b101 "
b101 g
b11111100 )
b11111100 c
b1 '
b1 e
b10 (
b10 d
b101 !
b101 h
b10100101 *
b10100101 b
b10100011 +
b10100011 a
b10100010 ,
b10100010 `
b11 .
b11 ^
b10 /
b10 ]
16
#26000
b100100 L
#30000
0H
b11111111 J
b11111111 X
b1010101 D
b1010101 V
09
06
#35000
16
#36000
b100111 L
#40000
1H
1F
1G
b100110100 I
b100110100 W
b11100000 A
b11100000 S
b10111 C
b10111 U
b1000 B
b1000 T
b110100 J
b110100 X
b10110100 @
b10110100 R
b10111100 ?
b10111100 Q
b10101011 >
b10101011 P
b11100 <
b11100 N
b1011 ;
b1011 M
b10 =
b10 O
b101 D
b101 V
19
06
#45000
1%
1$
b100110100 "
b100110100 g
b11100000 )
b11100000 c
b10111 '
b10111 e
b1000 (
b1000 d
b110100 !
b110100 h
b10110100 *
b10110100 b
b10111100 +
b10111100 a
b10101011 ,
b10101011 `
b11100 .
b11100 ^
b1011 /
b1011 ]
b10 -
b10 _
b101 &
b101 f
16
#46000
b110111 L
#48000
0#
0%
00
0$
b0 "
b0 g
b0 )
b0 c
b0 '
b0 e
b0 (
b0 d
b0 !
b0 h
b0 *
b0 b
b0 +
b0 a
b0 ,
b0 `
b0 .
b0 ^
b0 /
b0 ]
b0 -
b0 _
b0 &
b0 f
0E
#49000
b1001001 L
