rtl/v4/ifa_relation_memory_controller.sv
//======================================================================
// IFÁ Processor V4
//
// Relation Memory Controller
//
// WIDTH = 8
// FRAME = {Y, RA, RD, R0, T}
// KEY   = {RA, RD, T}
// DEPTH = 16
// HIT   = exact key match
// EVICT = FIFO
//======================================================================

module ifa_relation_memory_controller #(
    parameter WIDTH = 8,
    parameter DEPTH = 16
)(
    input  logic                     clk,
    input  logic                     rst,

    input  logic                     req_valid,

    input  logic [WIDTH-1:0]         in_y,
    input  logic [WIDTH-1:0]         in_ra,
    input  logic [WIDTH-1:0]         in_rd,
    input  logic [WIDTH-1:0]         in_r0,
    input  logic [WIDTH-1:0]         in_t,

    output logic                     hit,
    output logic                     miss,

    output logic [WIDTH-1:0]         out_y,
    output logic [WIDTH-1:0]         out_ra,
    output logic [WIDTH-1:0]         out_rd,
    output logic [WIDTH-1:0]         out_r0,
    output logic [WIDTH-1:0]         out_t,

    output logic [31:0]              hit_count,
    output logic [31:0]              miss_count,
    output logic [31:0]              store_count,
    output logic [31:0]              evict_count
);

    localparam INDEX_W = $clog2(DEPTH);

    // ------------------------------------------------------------
    // Storage
    // ------------------------------------------------------------

    logic [WIDTH-1:0] mem_y  [0:DEPTH-1];
    logic [WIDTH-1:0] mem_ra [0:DEPTH-1];
    logic [WIDTH-1:0] mem_rd [0:DEPTH-1];
    logic [WIDTH-1:0] mem_r0 [0:DEPTH-1];
    logic [WIDTH-1:0] mem_t  [0:DEPTH-1];

    logic valid [0:DEPTH-1];

    logic [INDEX_W-1:0] fifo_ptr;

    // ------------------------------------------------------------
    // Lookup combinational logic
    // ------------------------------------------------------------

    logic lookup_hit;
    logic [INDEX_W-1:0] lookup_index;

    integer i;

    always_comb begin
        lookup_hit   = 1'b0;
        lookup_index = '0;

        for (int j = 0; j < DEPTH; j = j + 1) begin
            if (
                valid[j] &&
                mem_ra[j] == in_ra &&
                mem_rd[j] == in_rd &&
                mem_t [j] == in_t
            ) begin
                lookup_hit   = 1'b1;
                lookup_index = j;
            end
        end
    end

    // ------------------------------------------------------------
    // Sequential controller
    // ------------------------------------------------------------

    always_ff @(posedge clk) begin
        if (rst) begin
            fifo_ptr <= '0;

            hit  <= 1'b0;
            miss <= 1'b0;

            out_y  <= '0;
            out_ra <= '0;
            out_rd <= '0;
            out_r0 <= '0;
            out_t  <= '0;

            hit_count   <= 32'd0;
            miss_count  <= 32'd0;
            store_count <= 32'd0;
            evict_count <= 32'd0;

            for (i = 0; i < DEPTH; i = i + 1) begin
                valid[i] <= 1'b0;

                mem_y [i] <= '0;
                mem_ra[i] <= '0;
                mem_rd[i] <= '0;
                mem_r0[i] <= '0;
                mem_t [i] <= '0;
            end

        end else begin
            hit  <= 1'b0;
            miss <= 1'b0;

            if (req_valid) begin

                if (lookup_hit) begin
                    // Cache hit: return stored full frame
                    hit  <= 1'b1;
                    miss <= 1'b0;

                    hit_count <= hit_count + 32'd1;

                    out_y  <= mem_y [lookup_index];
                    out_ra <= mem_ra[lookup_index];
                    out_rd <= mem_rd[lookup_index];
                    out_r0 <= mem_r0[lookup_index];
                    out_t  <= mem_t [lookup_index];

                end else begin
                    // Cache miss: store incoming frame at FIFO pointer
                    hit  <= 1'b0;
                    miss <= 1'b1;

                    miss_count  <= miss_count + 32'd1;
                    store_count <= store_count + 32'd1;

                    mem_y [fifo_ptr] <= in_y;
                    mem_ra[fifo_ptr] <= in_ra;
                    mem_rd[fifo_ptr] <= in_rd;
                    mem_r0[fifo_ptr] <= in_r0;
                    mem_t [fifo_ptr] <= in_t;
                    if (valid[fifo_ptr]) begin
                        evict_count <= evict_count + 32'd1;
                    end

                    valid[fifo_ptr]  <= 1'b1;

                    out_y  <= in_y;
                    out_ra <= in_ra;
                    out_rd <= in_rd;
                    out_r0 <= in_r0;
                    out_t  <= in_t;

                    fifo_ptr <= fifo_ptr + 1'b1;
                end

            end
        end
    end

endmodule

rtl/v4/ifa_v4_core.sv
//======================================================================
// IFÁ Processor V4 Core Wrapper
//
// Wraps Relation Memory Controller around incoming RPC frame.
//
// Input frame:
//   rpc_y, rpc_ra, rpc_rd, rpc_r0, rpc_t
//
// Output frame:
//   out_y, out_ra, out_rd, out_r0, out_t
//
// On HIT:
//   outputs stored frame
//
// On MISS:
//   stores incoming RPC frame and outputs it
//======================================================================

module ifa_v4_core #(
    parameter WIDTH = 8,
    parameter DEPTH = 16
)(
    input  logic                     clk,
    input  logic                     rst,

    input  logic                     rpc_valid,

    input  logic [WIDTH-1:0]         rpc_y,
    input  logic [WIDTH-1:0]         rpc_ra,
    input  logic [WIDTH-1:0]         rpc_rd,
    input  logic [WIDTH-1:0]         rpc_r0,
    input  logic [WIDTH-1:0]         rpc_t,

    output logic                     rmu_hit,
    output logic                     rmu_miss,

    output logic [WIDTH-1:0]         out_y,
    output logic [WIDTH-1:0]         out_ra,
    output logic [WIDTH-1:0]         out_rd,
    output logic [WIDTH-1:0]         out_r0,
    output logic [WIDTH-1:0]         out_t,

    output logic [31:0]              hit_count,
    output logic [31:0]              miss_count,
    output logic [31:0]              store_count,
    output logic [31:0]              evict_count
);

    ifa_relation_memory_controller #(
        .WIDTH(WIDTH),
        .DEPTH(DEPTH)
    ) rmc (
        .clk(clk),
        .rst(rst),

        .req_valid(rpc_valid),

        .in_y(rpc_y),
        .in_ra(rpc_ra),
        .in_rd(rpc_rd),
        .in_r0(rpc_r0),
        .in_t(rpc_t),

        .hit(rmu_hit),
        .miss(rmu_miss),

        .out_y(out_y),
        .out_ra(out_ra),
        .out_rd(out_rd),
        .out_r0(out_r0),
        .out_t(out_t),

        .hit_count(hit_count),
        .miss_count(miss_count),
        .store_count(store_count),
        .evict_count(evict_count)
    );

endmodule

rtl/v4/ifa_rpc_stub.sv
//======================================================================
// IFÁ Processor V4
//
// RPC Stub
//
// Inputs:
//   A, B
//
// Produces Relation Frame:
//   Y  = A + B
//   RA = A & B
//   RD = A ^ B
//   R0 = ~(A | B)
//   T  = RD ^ Y
//
// WIDTH = 8
//======================================================================

module ifa_rpc_stub #(
    parameter WIDTH = 8
)(
    input  logic [WIDTH-1:0] A,
    input  logic [WIDTH-1:0] B,

    output logic [WIDTH-1:0] Y,
    output logic [WIDTH-1:0] RA,
    output logic [WIDTH-1:0] RD,
    output logic [WIDTH-1:0] R0,
    output logic [WIDTH-1:0] T
);

    integer i;

    always_comb begin
        Y  = A + B;
        RA = A & B;
        RD = A ^ B;
        R0 = ~(A | B);
        T  = RD ^ Y;

    end

endmodule

rtl/v4/ifa_v4_end_to_end_core.sv
//======================================================================
// IFÁ Processor V4 End-to-End Core
//
// A,B → RPC Stub → Relation Frame → RMU → Output
//======================================================================

module ifa_v4_end_to_end_core #(
    parameter WIDTH = 8,
    parameter DEPTH = 16
)(
    input  logic                     clk,
    input  logic                     rst,

    input  logic                     in_valid,
    input  logic [WIDTH-1:0]         A,
    input  logic [WIDTH-1:0]         B,

    output logic                     rmu_hit,
    output logic                     rmu_miss,

    output logic [WIDTH-1:0]         out_y,
    output logic [WIDTH-1:0]         out_ra,
    output logic [WIDTH-1:0]         out_rd,
    output logic [WIDTH-1:0]         out_r0,
    output logic [WIDTH-1:0]         out_t,

    output logic [31:0]              hit_count,
    output logic [31:0]              miss_count,
    output logic [31:0]              store_count,
    output logic [31:0]              evict_count
);

    logic [WIDTH-1:0] rpc_y;
    logic [WIDTH-1:0] rpc_ra;
    logic [WIDTH-1:0] rpc_rd;
    logic [WIDTH-1:0] rpc_r0;
    logic [WIDTH-1:0] rpc_t;

    ifa_rpc_stub #(
        .WIDTH(WIDTH)
    ) rpc (
        .A(A),
        .B(B),

        .Y(rpc_y),
        .RA(rpc_ra),
        .RD(rpc_rd),
        .R0(rpc_r0),
        .T(rpc_t)
    );

    ifa_v4_core #(
        .WIDTH(WIDTH),
        .DEPTH(DEPTH)
    ) core (
        .clk(clk),
        .rst(rst),

        .rpc_valid(in_valid),

        .rpc_y(rpc_y),
        .rpc_ra(rpc_ra),
        .rpc_rd(rpc_rd),
        .rpc_r0(rpc_r0),
        .rpc_t(rpc_t),

        .rmu_hit(rmu_hit),
        .rmu_miss(rmu_miss),

        .out_y(out_y),
        .out_ra(out_ra),
        .out_rd(out_rd),
        .out_r0(out_r0),
        .out_t(out_t),

        .hit_count(hit_count),
        .miss_count(miss_count),
        .store_count(store_count),
        .evict_count(evict_count)
    );

endmodule

tb/v4/tb_v4_gtkwave_overall.sv
`timescale 1ns/1ps
module tb_v4_gtkwave_overall;
    parameter WIDTH = 8;
    parameter DEPTH = 16;

    logic clk, rst, in_valid;
    logic [WIDTH-1:0] A, B;
    logic rmu_hit, rmu_miss;
    logic [WIDTH-1:0] out_y, out_ra, out_rd, out_r0, out_t;
    logic [31:0] hit_count, miss_count, store_count, evict_count;

    ifa_v4_end_to_end_core #(.WIDTH(WIDTH), .DEPTH(DEPTH)) dut (
        .clk(clk), .rst(rst), .in_valid(in_valid), .A(A), .B(B),
        .rmu_hit(rmu_hit), .rmu_miss(rmu_miss),
        .out_y(out_y), .out_ra(out_ra), .out_rd(out_rd), .out_r0(out_r0), .out_t(out_t),
        .hit_count(hit_count), .miss_count(miss_count), .store_count(store_count), .evict_count(evict_count)
    );

    always #5 clk = ~clk;

    logic [WIDTH-1:0] test_a [0:11];
    logic [WIDTH-1:0] test_b [0:11];
    integer i;

    initial begin
        test_a[0]  = 8'h0D; test_b[0]  = 8'h06;
        test_a[1]  = 8'h0D; test_b[1]  = 8'h06; // repeat -> expect hit
        test_a[2]  = 8'h07; test_b[2]  = 8'h08;
        test_a[3]  = 8'h01; test_b[3]  = 8'h02;
        test_a[4]  = 8'h07; test_b[4]  = 8'h08; // repeat -> expect hit
        test_a[5]  = 8'h00; test_b[5]  = 8'h00;
        test_a[6]  = 8'hFF; test_b[6]  = 8'hFF;
        test_a[7]  = 8'h01; test_b[7]  = 8'h02; // repeat -> expect hit
        test_a[8]  = 8'h21; test_b[8]  = 8'h42;
        test_a[9]  = 8'h21; test_b[9]  = 8'h42; // repeat -> expect hit
        test_a[10] = 8'hA5; test_b[10] = 8'h5A;
        test_a[11] = 8'h00; test_b[11] = 8'h00; // repeat -> expect hit
    end

    initial begin
        $dumpfile("sim/v4/gtkwave_overall.vcd");
        $dumpvars(0, tb_v4_gtkwave_overall);

        clk = 0; rst = 1; in_valid = 0; A = 0; B = 0;
        repeat (2) @(posedge clk);
        @(negedge clk);
        rst = 0;

        $display("=========================================================");
        $display("V4 GTKWAVE OVERALL TEST -- post RA/T patch (race-free)");
        $display("=========================================================");

        for (i = 0; i < 12; i = i + 1) begin
            @(negedge clk);
            A = test_a[i];
            B = test_b[i];
            in_valid = 1;

            @(posedge clk);
            #1;

            $display("[%0d] A=0x%0h B=0x%0h | hit=%0b miss=%0b | Y=0x%0h RA=0x%0h RD=0x%0h R0=0x%0h T=0x%0h | hits=%0d misses=%0d",
                      i, A, B, rmu_hit, rmu_miss, out_y, out_ra, out_rd, out_r0, out_t,
                      hit_count, miss_count);

            @(negedge clk);
            in_valid = 0;
        end

        @(posedge clk);

        $display("=========================================================");
        $display("FINAL COUNTS: hits=%0d misses=%0d stores=%0d evicts=%0d",
                  hit_count, miss_count, store_count, evict_count);
        $display("Expected: hits=5 misses=7 (7 unique pairs + 5 repeats)");
        $display("Done. Open sim/v4/gtkwave_overall.vcd in GTKWave to inspect.");
        $display("=========================================================");
        $finish;
    end
endmodule

sim/v4/gtkwave_overall.vcd
$date
	Thu Jul  9 21:49:58 2026
$end
$version
	Icarus Verilog
$end
$timescale
	1ps
$end
$scope module tb_v4_gtkwave_overall $end
$var wire 32 ! store_count [31:0] $end
$var wire 1 " rmu_miss $end
$var wire 1 # rmu_hit $end
$var wire 8 $ out_y [7:0] $end
$var wire 8 % out_t [7:0] $end
$var wire 8 & out_rd [7:0] $end
$var wire 8 ' out_ra [7:0] $end
$var wire 8 ( out_r0 [7:0] $end
$var wire 32 ) miss_count [31:0] $end
$var wire 32 * hit_count [31:0] $end
$var wire 32 + evict_count [31:0] $end
$var parameter 32 , DEPTH $end
$var parameter 32 - WIDTH $end
$var reg 8 . A [7:0] $end
$var reg 8 / B [7:0] $end
$var reg 1 0 clk $end
$var reg 1 1 in_valid $end
$var reg 1 2 rst $end
$var integer 32 3 i [31:0] $end
$scope module dut $end
$var wire 8 4 A [7:0] $end
$var wire 8 5 B [7:0] $end
$var wire 1 0 clk $end
$var wire 1 1 in_valid $end
$var wire 1 2 rst $end
$var wire 32 6 store_count [31:0] $end
$var wire 8 7 rpc_y [7:0] $end
$var wire 8 8 rpc_t [7:0] $end
$var wire 8 9 rpc_rd [7:0] $end
$var wire 8 : rpc_ra [7:0] $end
$var wire 8 ; rpc_r0 [7:0] $end
$var wire 1 " rmu_miss $end
$var wire 1 # rmu_hit $end
$var wire 8 < out_y [7:0] $end
$var wire 8 = out_t [7:0] $end
$var wire 8 > out_rd [7:0] $end
$var wire 8 ? out_ra [7:0] $end
$var wire 8 @ out_r0 [7:0] $end
$var wire 32 A miss_count [31:0] $end
$var wire 32 B hit_count [31:0] $end
$var wire 32 C evict_count [31:0] $end
$var parameter 32 D DEPTH $end
$var parameter 32 E WIDTH $end
$scope module core $end
$var wire 1 0 clk $end
$var wire 1 1 rpc_valid $end
$var wire 1 2 rst $end
$var wire 32 F store_count [31:0] $end
$var wire 8 G rpc_y [7:0] $end
$var wire 8 H rpc_t [7:0] $end
$var wire 8 I rpc_rd [7:0] $end
$var wire 8 J rpc_ra [7:0] $end
$var wire 8 K rpc_r0 [7:0] $end
$var wire 1 " rmu_miss $end
$var wire 1 # rmu_hit $end
$var wire 8 L out_y [7:0] $end
$var wire 8 M out_t [7:0] $end
$var wire 8 N out_rd [7:0] $end
$var wire 8 O out_ra [7:0] $end
$var wire 8 P out_r0 [7:0] $end
$var wire 32 Q miss_count [31:0] $end
$var wire 32 R hit_count [31:0] $end
$var wire 32 S evict_count [31:0] $end
$var parameter 32 T DEPTH $end
$var parameter 32 U WIDTH $end
$scope module rmc $end
$var wire 1 0 clk $end
$var wire 1 1 req_valid $end
$var wire 1 2 rst $end
$var wire 8 V in_y [7:0] $end
$var wire 8 W in_t [7:0] $end
$var wire 8 X in_rd [7:0] $end
$var wire 8 Y in_ra [7:0] $end
$var wire 8 Z in_r0 [7:0] $end
$var parameter 32 [ DEPTH $end
$var parameter 32 \ INDEX_W $end
$var parameter 32 ] WIDTH $end
$var reg 32 ^ evict_count [31:0] $end
$var reg 4 _ fifo_ptr [3:0] $end
$var reg 1 # hit $end
$var reg 32 ` hit_count [31:0] $end
$var reg 1 a lookup_hit $end
$var reg 4 b lookup_index [3:0] $end
$var reg 1 " miss $end
$var reg 32 c miss_count [31:0] $end
$var reg 8 d out_r0 [7:0] $end
$var reg 8 e out_ra [7:0] $end
$var reg 8 f out_rd [7:0] $end
$var reg 8 g out_t [7:0] $end
$var reg 8 h out_y [7:0] $end
$var reg 32 i store_count [31:0] $end
$var integer 32 j i [31:0] $end
$scope begin $ivl_for_loop0 $end
$var integer 32 k j [31:0] $end
$upscope $end
$upscope $end
$upscope $end
$scope module rpc $end
$var wire 8 l A [7:0] $end
$var wire 8 m B [7:0] $end
$var parameter 32 n WIDTH $end
$var reg 8 o R0 [7:0] $end
$var reg 8 p RA [7:0] $end
$var reg 8 q RD [7:0] $end
$var reg 8 r T [7:0] $end
$var reg 8 s Y [7:0] $end
$upscope $end
$upscope $end
$upscope $end
$enddefinitions $end
$comment Show the parameter values. $end
$dumpall
b1000 n
b1000 ]
b100 \
b10000 [
b1000 U
b10000 T
b1000 E
b10000 D
b1000 -
b10000 ,
$end
#0
$dumpvars
b0 s
b0 r
b0 q
b0 p
b11111111 o
b0 m
b0 l
b10000 k
bx j
bx i
bx h
bx g
bx f
bx e
bx d
bx c
b0 b
0a
bx `
bx _
bx ^
b11111111 Z
b0 Y
b0 X
b0 W
b0 V
bx S
bx R
bx Q
bx P
bx O
bx N
bx M
bx L
b11111111 K
b0 J
b0 I
b0 H
b0 G
bx F
bx C
bx B
bx A
bx @
bx ?
bx >
bx =
bx <
b11111111 ;
b0 :
b0 9
b0 8
b0 7
bx 6
b0 5
b0 4
bx 3
12
01
00
b0 /
b0 .
bx +
bx *
bx )
bx (
bx '
bx &
bx %
bx $
x#
x"
bx !
$end
#5000
b10000 k
b0 +
b0 C
b0 S
b0 ^
b0 !
b0 6
b0 F
b0 i
b0 )
b0 A
b0 Q
b0 c
b0 *
b0 B
b0 R
b0 `
b0 %
b0 =
b0 M
b0 g
b0 (
b0 @
b0 P
b0 d
b0 &
b0 >
b0 N
b0 f
b0 '
b0 ?
b0 O
b0 e
b0 $
b0 <
b0 L
b0 h
0"
0#
b0 _
b10000 j
10
#10000
00
#15000
b10000 j
10
#20000
b0 3
02
00
#25000
10
#30000
b10000 k
b11000 8
b11000 H
b11000 W
b11000 r
b11110000 ;
b11110000 K
b11110000 Z
b11110000 o
b1011 9
b1011 I
b1011 X
b1011 q
b100 :
b100 J
b100 Y
b100 p
b10011 7
b10011 G
b10011 V
b10011 s
11
b110 /
b110 5
b110 m
b1101 .
b1101 4
b1101 l
00
#35000
1a
b10000 k
b1 _
b11000 %
b11000 =
b11000 M
b11000 g
b11110000 (
b11110000 @
b11110000 P
b11110000 d
b1011 &
b1011 >
b1011 N
b1011 f
b100 '
b100 ?
b100 O
b100 e
b10011 $
b10011 <
b10011 L
b10011 h
b1 !
b1 6
b1 F
b1 i
b1 )
b1 A
b1 Q
b1 c
1"
10
#40000
b1 3
01
00
#45000
0"
10
#50000
11
00
#55000
b1 *
b1 B
b1 R
b1 `
1#
10
#60000
b10 3
01
00
#65000
0#
10
#70000
b10000 k
0a
b0 8
b0 H
b0 W
b0 r
b1111 9
b1111 I
b1111 X
b1111 q
b0 :
b0 J
b0 Y
b0 p
b1111 7
b1111 G
b1111 V
b1111 s
11
b1000 /
b1000 5
b1000 m
b111 .
b111 4
b111 l
00
#75000
b1 b
1a
b10000 k
b10 _
b0 %
b0 =
b0 M
b0 g
b1111 &
b1111 >
b1111 N
b1111 f
b0 '
b0 ?
b0 O
b0 e
b1111 $
b1111 <
b1111 L
b1111 h
b10 !
b10 6
b10 F
b10 i
b10 )
b10 A
b10 Q
b10 c
1"
10
#80000
b11 3
01
00
#85000
0"
10
#90000
b10000 k
b0 b
0a
b11111100 ;
b11111100 K
b11111100 Z
b11111100 o
b11 9
b11 I
b11 X
b11 q
b11 7
b11 G
b11 V
b11 s
11
b10 /
b10 5
b10 m
b1 .
b1 4
b1 l
00
#95000
b10 b
1a
b10000 k
b11 _
b11111100 (
b11111100 @
b11111100 P
b11111100 d
b11 &
b11 >
b11 N
b11 f
b11 $
b11 <
b11 L
b11 h
b11 !
b11 6
b11 F
b11 i
b11 )
b11 A
b11 Q
b11 c
1"
10
#100000
b100 3
01
00
#105000
0"
10
#110000
b10000 k
b1 b
1a
b11110000 ;
b11110000 K
b11110000 Z
b11110000 o
b1111 9
b1111 I
b1111 X
b1111 q
b1111 7
b1111 G
b1111 V
b1111 s
11
b1000 /
b1000 5
b1000 m
b111 .
b111 4
b111 l
00
#115000
b11110000 (
b11110000 @
b11110000 P
b11110000 d
b1111 &
b1111 >
b1111 N
b1111 f
b1111 $
b1111 <
b1111 L
b1111 h
b10 *
b10 B
b10 R
b10 `
1#
10
#120000
b101 3
01
00
#125000
0#
10
#130000
b10000 k
b0 b
0a
b11111111 ;
b11111111 K
b11111111 Z
b11111111 o
b0 9
b0 I
b0 X
b0 q
b0 7
b0 G
b0 V
b0 s
11
b0 /
b0 5
b0 m
b0 .
b0 4
b0 l
00
#135000
b11 b
1a
b10000 k
b100 _
b11111111 (
b11111111 @
b11111111 P
b11111111 d
b0 &
b0 >
b0 N
b0 f
b0 $
b0 <
b0 L
b0 h
b100 !
b100 6
b100 F
b100 i
b100 )
b100 A
b100 Q
b100 c
1"
10
#140000
b110 3
01
00
#145000
0"
10
#150000
b10000 k
b0 b
0a
b11111110 8
b11111110 H
b11111110 W
b11111110 r
b0 ;
b0 K
b0 Z
b0 o
b11111111 :
b11111111 J
b11111111 Y
b11111111 p
b11111110 7
b11111110 G
b11111110 V
b11111110 s
11
b11111111 /
b11111111 5
b11111111 m
b11111111 .
b11111111 4
b11111111 l
00
#155000
b100 b
1a
b10000 k
b101 _
b11111110 %
b11111110 =
b11111110 M
b11111110 g
b0 (
b0 @
b0 P
b0 d
b11111111 '
b11111111 ?
b11111111 O
b11111111 e
b11111110 $
b11111110 <
b11111110 L
b11111110 h
b101 !
b101 6
b101 F
b101 i
b101 )
b101 A
b101 Q
b101 c
1"
10
#160000
b111 3
01
00
#165000
0"
10
#170000
b10000 k
b10 b
1a
b0 8
b0 H
b0 W
b0 r
b11111100 ;
b11111100 K
b11111100 Z
b11111100 o
b11 9
b11 I
b11 X
b11 q
b0 :
b0 J
b0 Y
b0 p
b11 7
b11 G
b11 V
b11 s
11
b10 /
b10 5
b10 m
b1 .
b1 4
b1 l
00
#175000
b0 %
b0 =
b0 M
b0 g
b11111100 (
b11111100 @
b11111100 P
b11111100 d
b11 &
b11 >
b11 N
b11 f
b0 '
b0 ?
b0 O
b0 e
b11 $
b11 <
b11 L
b11 h
b11 *
b11 B
b11 R
b11 `
1#
10
#180000
b1000 3
01
00
#185000
0#
10
#190000
b10000 k
b0 b
0a
b10011100 ;
b10011100 K
b10011100 Z
b10011100 o
b1100011 9
b1100011 I
b1100011 X
b1100011 q
b1100011 7
b1100011 G
b1100011 V
b1100011 s
11
b1000010 /
b1000010 5
b1000010 m
b100001 .
b100001 4
b100001 l
00
#195000
b101 b
1a
b10000 k
b110 _
b10011100 (
b10011100 @
b10011100 P
b10011100 d
b1100011 &
b1100011 >
b1100011 N
b1100011 f
b1100011 $
b1100011 <
b1100011 L
b1100011 h
b110 !
b110 6
b110 F
b110 i
b110 )
b110 A
b110 Q
b110 c
1"
10
#200000
b1001 3
01
00
#205000
0"
10
#210000
11
00
#215000
b100 *
b100 B
b100 R
b100 `
1#
10
#220000
b1010 3
01
00
#225000
0#
10
#230000
b10000 k
b0 b
0a
b0 ;
b0 K
b0 Z
b0 o
b11111111 9
b11111111 I
b11111111 X
b11111111 q
b11111111 7
b11111111 G
b11111111 V
b11111111 s
11
b1011010 /
b1011010 5
b1011010 m
b10100101 .
b10100101 4
b10100101 l
00
#235000
b110 b
1a
b10000 k
b111 _
b0 (
b0 @
b0 P
b0 d
b11111111 &
b11111111 >
b11111111 N
b11111111 f
b11111111 $
b11111111 <
b11111111 L
b11111111 h
b111 !
b111 6
b111 F
b111 i
b111 )
b111 A
b111 Q
b111 c
1"
10
#240000
b1011 3
01
00
#245000
0"
10
#250000
b10000 k
b11 b
1a
b11111111 ;
b11111111 K
b11111111 Z
b11111111 o
b0 9
b0 I
b0 X
b0 q
b0 7
b0 G
b0 V
b0 s
11
b0 /
b0 5
b0 m
b0 .
b0 4
b0 l
00
#255000
b11111111 (
b11111111 @
b11111111 P
b11111111 d
b0 &
b0 >
b0 N
b0 f
b0 $
b0 <
b0 L
b0 h
b101 *
b101 B
b101 R
b101 `
1#
10
#260000
b1100 3
01
00
#265000
0#
10
