rtl/v4/ifa_onile_supervisor.sv
//======================================================================
// IFÁ Processor V4
// ONÍLẸ̀ Supervisor
// Generic Cross-YÀRÁ Permission Controller
//
// Rules:
//
//   1. Local access is always allowed:
//
//          source_yara == destination_yara
//
//   2. Cross-YÀRÁ access requires explicit permission:
//
//          source_yara != destination_yara
//
//   3. Babaláwo mode is required only to grant or revoke permission.
//
//   4. Once granted, permission remains active until revoked.
//
//   5. Invalid source or destination IDs are denied.
//
// Permission matrix:
//
//      share_permission[source][destination]
//
// YÀRÁ identity is not added to the relation key.
//======================================================================

module ifa_onile_supervisor #(
    // Temporary compatibility parameter.
    parameter integer YARA_COUNT = 2,

    // Official V4 operating-system capacity parameter.
    parameter integer MAX_YARA = YARA_COUNT,

    parameter integer YARA_W =
        (MAX_YARA <= 1) ? 1 : $clog2(MAX_YARA)
)(
    input  logic                    clk,
    input  logic                    rst,

    // Administrative privilege level.
    input  logic                    babalawo_mode,

    // Permission administration.
    input  logic                    grant_valid,
    input  logic                    revoke_valid,

    input  logic [YARA_W-1:0]       admin_source_yara,
    input  logic [YARA_W-1:0]       admin_destination_yara,

    // Runtime access/delegation request.
    input  logic                    share_request,
    input  logic [YARA_W-1:0]       request_source_yara,
    input  logic [YARA_W-1:0]       request_destination_yara,

    output logic                    share_allowed,
    output logic                    share_denied,

    // Verification and statistics.
    output logic                    explicit_permission,
    output logic [31:0]             allowed_count,
    output logic [31:0]             denied_count
);

    //==================================================================
    // Parameter validation
    //==================================================================

    initial begin
        if (MAX_YARA < 1) begin
            $error(
                "ifa_onile_supervisor: MAX_YARA must be at least 1"
            );
            $finish;
        end
    end

    //==================================================================
    // Permission matrix
    //
    // permission[src][dst] authorizes cross-YÀRÁ transfer.
    // Self-access does not require an entry.
    //==================================================================

    logic share_permission
        [0:MAX_YARA-1]
        [0:MAX_YARA-1];

    integer source_index;
    integer destination_index;

    //==================================================================
    // ID validation
    //==================================================================

    logic admin_source_valid;
    logic admin_destination_valid;

    logic request_source_valid;
    logic request_destination_valid;

    always_comb begin
        admin_source_valid =
            (admin_source_yara < MAX_YARA);

        admin_destination_valid =
            (admin_destination_yara < MAX_YARA);

        request_source_valid =
            (request_source_yara < MAX_YARA);

        request_destination_valid =
            (request_destination_yara < MAX_YARA);
    end

    //==================================================================
    // Local-access detection
    //==================================================================

    logic local_access;

    always_comb begin
        local_access =
            request_source_valid &&
            request_destination_valid &&
            (request_source_yara == request_destination_yara);
    end

    //==================================================================
    // Administrative permission operations
    //
    // Permission entries are only needed between different YÀRÁ.
    //==================================================================

    logic grant_accepted;
    logic revoke_accepted;

    always_comb begin
        grant_accepted =
            babalawo_mode &&
            grant_valid &&
            admin_source_valid &&
            admin_destination_valid &&
            (admin_source_yara != admin_destination_yara);

        revoke_accepted =
            babalawo_mode &&
            revoke_valid &&
            admin_source_valid &&
            admin_destination_valid &&
            (admin_source_yara != admin_destination_yara);
    end

    //==================================================================
    // Explicit cross-YÀRÁ permission lookup
    //==================================================================

    always_comb begin
        explicit_permission = 1'b0;

        if (
            request_source_valid &&
            request_destination_valid &&
            (request_source_yara != request_destination_yara)
        ) begin
            explicit_permission =
                share_permission
                    [request_source_yara]
                    [request_destination_yara];
        end
    end

    //==================================================================
    // Runtime authorization
    //
    // Local request:
    //
    //      source == destination
    //
    // is always allowed.
    //
    // Cross-YÀRÁ request:
    //
    //      source != destination
    //
    // requires an explicit permission entry.
    //==================================================================

    always_comb begin
        share_allowed = 1'b0;
        share_denied  = 1'b0;

        if (share_request) begin
            if (
                !request_source_valid ||
                !request_destination_valid
            ) begin
                share_denied = 1'b1;
            end
            else if (local_access) begin
                // SHARE is reserved for cross-YÀRÁ delegation.
                // A room never delegates a frame to itself.
                share_denied = 1'b1;
            end
            else if (explicit_permission) begin
                share_allowed = 1'b1;
            end
            else begin
                share_denied = 1'b1;
            end
        end
    end

    //==================================================================
    // Permission matrix and statistics
    //==================================================================

    always_ff @(posedge clk) begin
        if (rst) begin
            allowed_count <= 32'd0;
            denied_count  <= 32'd0;

            for (
                source_index = 0;
                source_index < MAX_YARA;
                source_index = source_index + 1
            ) begin
                for (
                    destination_index = 0;
                    destination_index < MAX_YARA;
                    destination_index = destination_index + 1
                ) begin
                    share_permission
                        [source_index]
                        [destination_index] <= 1'b0;
                end
            end
        end
        else begin

            //----------------------------------------------------------
            // Grant permission
            //----------------------------------------------------------

            if (grant_accepted) begin
                share_permission
                    [admin_source_yara]
                    [admin_destination_yara] <= 1'b1;
            end

            //----------------------------------------------------------
            // Revoke permission
            //
            // Revoke wins if grant and revoke target the same entry
            // during the same clock cycle.
            //----------------------------------------------------------

            if (revoke_accepted) begin
                share_permission
                    [admin_source_yara]
                    [admin_destination_yara] <= 1'b0;
            end

            //----------------------------------------------------------
            // Runtime authorization counters
            //----------------------------------------------------------

            if (share_request) begin
                if (share_allowed) begin
                    allowed_count <= allowed_count + 32'd1;
                end
                else begin
                    denied_count <= denied_count + 32'd1;
                end
            end
        end
    end

endmodule

tb/v4/tb_ifa_onile_supervisor.sv
`timescale 1ns/1ps

module tb_ifa_onile_supervisor;

    localparam integer YARA_COUNT = 2;
    localparam integer YARA_W = 1;

    logic clk;
    logic rst;

    logic babalawo_mode;

    logic grant_valid;
    logic revoke_valid;

    logic [YARA_W-1:0] admin_source_yara;
    logic [YARA_W-1:0] admin_destination_yara;

    logic share_request;
    logic [YARA_W-1:0] request_source_yara;
    logic [YARA_W-1:0] request_destination_yara;

    logic share_allowed;
    logic share_denied;
    logic explicit_permission;

    logic [31:0] allowed_count;
    logic [31:0] denied_count;

    ifa_onile_supervisor #(
        .YARA_COUNT(YARA_COUNT)
    ) dut (
        .clk(clk),
        .rst(rst),

        .babalawo_mode(babalawo_mode),

        .grant_valid(grant_valid),
        .revoke_valid(revoke_valid),

        .admin_source_yara(admin_source_yara),
        .admin_destination_yara(admin_destination_yara),

        .share_request(share_request),
        .request_source_yara(request_source_yara),
        .request_destination_yara(request_destination_yara),

        .share_allowed(share_allowed),
        .share_denied(share_denied),

        .explicit_permission(explicit_permission),
        .allowed_count(allowed_count),
        .denied_count(denied_count)
    );

    always #5 clk = ~clk;

    task automatic request_share(
        input logic src,
        input logic dst
    );
    begin
        @(negedge clk);

        request_source_yara      = src;
        request_destination_yara = dst;
        share_request            = 1'b1;

        $display("REQUEST YARA %0d -> YARA %0d | babalawo=%0d permission=%0d allowed=%0d denied=%0d",
                 src, dst, babalawo_mode, explicit_permission,
                 share_allowed, share_denied);

        @(negedge clk);
        share_request = 1'b0;
    end
    endtask

    task automatic grant_share(
        input logic src,
        input logic dst
    );
    begin
        @(negedge clk);

        admin_source_yara      = src;
        admin_destination_yara = dst;
        grant_valid            = 1'b1;

        @(negedge clk);
        grant_valid = 1'b0;

        #1;

        $display(
            "ONILE GRANT: YARA %0d -> YARA %0d",
            src,
            dst
        );
    end
    endtask

    task automatic revoke_share(
        input logic src,
        input logic dst
    );
    begin
        @(negedge clk);

        admin_source_yara      = src;
        admin_destination_yara = dst;
        revoke_valid           = 1'b1;

        @(negedge clk);
        revoke_valid = 1'b0;

        #1;

        $display(
            "ONILE REVOKE: YARA %0d -> YARA %0d",
            src,
            dst
        );
    end
    endtask

    initial begin
        $dumpfile("sim/v4/ifa_onile_supervisor.vcd");
        $dumpvars(0, tb_ifa_onile_supervisor);

        clk = 0;
        rst = 1;

        babalawo_mode = 0;

        grant_valid  = 0;
        revoke_valid = 0;

        admin_source_yara      = 0;
        admin_destination_yara = 0;

        share_request            = 0;
        request_source_yara      = 0;
        request_destination_yara = 0;

        repeat (3) @(negedge clk);
        rst = 0;

        $display("============================================================");
        $display("IFÁ V4 ONÍLẸ̀ PERMISSION TEST");
        $display("Isolation by default; sharing by authorization");
        $display("============================================================");

        //--------------------------------------------------------------
        // Test 1:
        // Same-room use is local and must always be allowed.
        //--------------------------------------------------------------

        request_share(0, 0);

        if (share_allowed !== 1'b1)
            $fatal(1, "Local YARA access should be allowed");

        //--------------------------------------------------------------
        // Test 2:
        // Cross-room use in normal mode must be denied.
        //--------------------------------------------------------------

        request_share(0, 1);

        if (share_denied !== 1'b1)
            $fatal(1, "Cross-YARA sharing must be denied in normal mode");

        //--------------------------------------------------------------
        // Test 3:
        // Entering Babaláwo mode alone does not grant permission.
        //--------------------------------------------------------------

        babalawo_mode = 1'b1;

        request_share(0, 1);

        if (share_denied !== 1'b1)
            $fatal(1, "Babalawo mode alone must not authorize sharing");

        //--------------------------------------------------------------
        // Test 4:
        // Onílẹ̀ explicitly grants YARA 0 -> YARA 1.
        //--------------------------------------------------------------

        grant_share(0, 1);

        request_share(0, 1);

        if (share_allowed !== 1'b1)
            $fatal(1, "Granted cross-YARA sharing should be allowed");

        //--------------------------------------------------------------
        // Test 5:
        // Permission is directional.
        // 0 -> 1 grant must not imply 1 -> 0.
        //--------------------------------------------------------------

        request_share(1, 0);

        if (share_denied !== 1'b1)
            $fatal(1, "Permission must remain directional");

        //--------------------------------------------------------------
        // Test 6:
        // Revoke permission and confirm access is denied again.
        //--------------------------------------------------------------

        revoke_share(0, 1);

        request_share(0, 1);

        if (share_denied !== 1'b1)
            $fatal(1, "Revoked sharing permission must be denied");

        //--------------------------------------------------------------
        // Test 7:
        // Leaving Babaláwo mode preserves isolation.
        //--------------------------------------------------------------

        babalawo_mode = 1'b0;

        request_share(0, 1);

        if (share_denied !== 1'b1)
            $fatal(1, "Normal mode must deny cross-YARA sharing");

        $display("");
        $display("FINAL COUNTERS");
        $display("------------------------------------------------------------");
        $display("Allowed requests = %0d", allowed_count);
        $display("Denied requests  = %0d", denied_count);

        $display("============================================================");
        $display("PASS: Local YÀRÁ access is allowed");
        $display("PASS: Cross-YÀRÁ sharing is denied by default");
        $display("PASS: Babaláwo mode alone does not bypass isolation");
        $display("PASS: Onílẹ̀ grants explicit directional permission");
        $display("PASS: Revocation restores isolation");
        $display("============================================================");

        $finish;
    end

endmodule

sim/v4/ifa_onile_supervisor.vcd
$date
	Fri Jul 10 20:35:32 2026
$end
$version
	Icarus Verilog
$end
$timescale
	1ps
$end
$scope module tb_ifa_onile_supervisor $end
$var wire 1 ! share_denied $end
$var wire 1 " share_allowed $end
$var wire 1 # explicit_permission $end
$var wire 32 $ denied_count [31:0] $end
$var wire 32 % allowed_count [31:0] $end
$var parameter 32 & YARA_COUNT $end
$var parameter 32 ' YARA_W $end
$var reg 1 ( admin_destination_yara $end
$var reg 1 ) admin_source_yara $end
$var reg 1 * babalawo_mode $end
$var reg 1 + clk $end
$var reg 1 , grant_valid $end
$var reg 1 - request_destination_yara $end
$var reg 1 . request_source_yara $end
$var reg 1 / revoke_valid $end
$var reg 1 0 rst $end
$var reg 1 1 share_request $end
$scope module dut $end
$var wire 1 ( admin_destination_yara $end
$var wire 1 ) admin_source_yara $end
$var wire 1 * babalawo_mode $end
$var wire 1 + clk $end
$var wire 1 , grant_valid $end
$var wire 1 - request_destination_yara $end
$var wire 1 . request_source_yara $end
$var wire 1 / revoke_valid $end
$var wire 1 0 rst $end
$var wire 1 1 share_request $end
$var parameter 32 2 MAX_YARA $end
$var parameter 32 3 YARA_COUNT $end
$var parameter 32 4 YARA_W $end
$var reg 1 5 admin_destination_valid $end
$var reg 1 6 admin_source_valid $end
$var reg 32 7 allowed_count [31:0] $end
$var reg 32 8 denied_count [31:0] $end
$var reg 1 # explicit_permission $end
$var reg 1 9 grant_accepted $end
$var reg 1 : local_access $end
$var reg 1 ; request_destination_valid $end
$var reg 1 < request_source_valid $end
$var reg 1 = revoke_accepted $end
$var reg 1 " share_allowed $end
$var reg 1 ! share_denied $end
$var integer 32 > destination_index [31:0] $end
$var integer 32 ? source_index [31:0] $end
$upscope $end
$scope task grant_share $end
$upscope $end
$scope task request_share $end
$upscope $end
$scope task revoke_share $end
$upscope $end
$upscope $end
$enddefinitions $end
$comment Show the parameter values. $end
$dumpall
b1 4
b10 3
b10 2
b1 '
b10 &
$end
#0
$dumpvars
bx ?
bx >
0=
1<
1;
1:
09
bx 8
bx 7
16
15
01
10
0/
0.
0-
0,
0+
0*
0)
0(
bx %
bx $
0#
0"
0!
$end
#5000
b0 $
b0 8
b0 %
b0 7
b10 >
b10 ?
1+
#10000
0+
#15000
b10 >
b10 ?
1+
#20000
0+
#25000
b10 >
b10 ?
1+
#30000
00
0+
#35000
1+
#40000
1"
11
0+
#45000
b1 %
b1 7
1+
#50000
0"
01
0+
#55000
1+
#60000
1!
0:
11
1-
0+
#65000
b1 $
b1 8
1+
#70000
0!
1*
01
0+
#75000
1+
#80000
1!
11
0+
#85000
b10 $
b10 8
1+
#90000
0!
01
0+
#95000
1+
#100000
19
1,
1(
0+
#105000
1#
1+
#110000
09
0,
0+
#115000
1+
#120000
1"
11
0+
#125000
b10 %
b10 7
1+
#130000
0"
01
0+
#135000
1+
#140000
1!
0#
11
0-
1.
0+
#145000
b11 $
b11 8
1+
#150000
0!
01
0+
#155000
1+
#160000
1=
1/
0+
#165000
1+
#170000
0=
0/
0+
#175000
1+
#180000
1!
11
1-
0.
0+
#185000
b100 $
b100 8
1+
#190000
0!
0*
01
0+
#195000
1+
#200000
1!
11
0+
#205000
b101 $
b101 8
1+
#210000
0!
01
0+
