rtl/v4/ifa_relation_memory_controller.sv
//======================================================================
// IFÁ Processor V4
//
// Relation Memory Controller
//
// WIDTH = 8
// FRAME = {Y, RA, RD, R0, T}
// KEY   = {RA, RD, T}
// DEPTH = 16
// HIT   = exact key match
// EVICT = FIFO
//======================================================================

module ifa_relation_memory_controller #(
    parameter WIDTH = 8,
    parameter DEPTH = 16
)(
    input  logic                     clk,
    input  logic                     rst,

    input  logic                     req_valid,

    input  logic [WIDTH-1:0]         in_y,
    input  logic [WIDTH-1:0]         in_ra,
    input  logic [WIDTH-1:0]         in_rd,
    input  logic [WIDTH-1:0]         in_r0,
    input  logic [WIDTH-1:0]         in_t,

    output logic                     hit,
    output logic                     miss,

    output logic [WIDTH-1:0]         out_y,
    output logic [WIDTH-1:0]         out_ra,
    output logic [WIDTH-1:0]         out_rd,
    output logic [WIDTH-1:0]         out_r0,
    output logic [WIDTH-1:0]         out_t,

    output logic [31:0]              hit_count,
    output logic [31:0]              miss_count,
    output logic [31:0]              store_count,
    output logic [31:0]              evict_count
);

    localparam INDEX_W = $clog2(DEPTH);

    // ------------------------------------------------------------
    // Storage
    // ------------------------------------------------------------

    logic [WIDTH-1:0] mem_y  [0:DEPTH-1];
    logic [WIDTH-1:0] mem_ra [0:DEPTH-1];
    logic [WIDTH-1:0] mem_rd [0:DEPTH-1];
    logic [WIDTH-1:0] mem_r0 [0:DEPTH-1];
    logic [WIDTH-1:0] mem_t  [0:DEPTH-1];

    logic valid [0:DEPTH-1];

    logic [INDEX_W-1:0] fifo_ptr;

    // ------------------------------------------------------------
    // Lookup combinational logic
    // ------------------------------------------------------------

    logic lookup_hit;
    logic [INDEX_W-1:0] lookup_index;

    integer i;

    always_comb begin
        lookup_hit   = 1'b0;
        lookup_index = '0;

        for (int j = 0; j < DEPTH; j = j + 1) begin
            if (
                valid[j] &&
                mem_ra[j] == in_ra &&
                mem_rd[j] == in_rd &&
                mem_t [j] == in_t
            ) begin
                lookup_hit   = 1'b1;
                lookup_index = j;
            end
        end
    end

    // ------------------------------------------------------------
    // Sequential controller
    // ------------------------------------------------------------

    always_ff @(posedge clk) begin
        if (rst) begin
            fifo_ptr <= '0;

            hit  <= 1'b0;
            miss <= 1'b0;

            out_y  <= '0;
            out_ra <= '0;
            out_rd <= '0;
            out_r0 <= '0;
            out_t  <= '0;

            hit_count   <= 32'd0;
            miss_count  <= 32'd0;
            store_count <= 32'd0;
            evict_count <= 32'd0;

            for (i = 0; i < DEPTH; i = i + 1) begin
                valid[i] <= 1'b0;

                mem_y [i] <= '0;
                mem_ra[i] <= '0;
                mem_rd[i] <= '0;
                mem_r0[i] <= '0;
                mem_t [i] <= '0;
            end

        end else begin
            hit  <= 1'b0;
            miss <= 1'b0;

            if (req_valid) begin

                if (lookup_hit) begin
                    // Cache hit: return stored full frame
                    hit  <= 1'b1;
                    miss <= 1'b0;

                    hit_count <= hit_count + 32'd1;

                    out_y  <= mem_y [lookup_index];
                    out_ra <= mem_ra[lookup_index];
                    out_rd <= mem_rd[lookup_index];
                    out_r0 <= mem_r0[lookup_index];
                    out_t  <= mem_t [lookup_index];

                end else begin
                    // Cache miss: store incoming frame at FIFO pointer
                    hit  <= 1'b0;
                    miss <= 1'b1;

                    miss_count  <= miss_count + 32'd1;
                    store_count <= store_count + 32'd1;

                    mem_y [fifo_ptr] <= in_y;
                    mem_ra[fifo_ptr] <= in_ra;
                    mem_rd[fifo_ptr] <= in_rd;
                    mem_r0[fifo_ptr] <= in_r0;
                    mem_t [fifo_ptr] <= in_t;
                    if (valid[fifo_ptr]) begin
                        evict_count <= evict_count + 32'd1;
                    end

                    valid[fifo_ptr]  <= 1'b1;

                    out_y  <= in_y;
                    out_ra <= in_ra;
                    out_rd <= in_rd;
                    out_r0 <= in_r0;
                    out_t  <= in_t;

                    fifo_ptr <= fifo_ptr + 1'b1;
                end

            end
        end
    end

endmodule

rtl/v4/ifa_v4_core.sv
//======================================================================
// IFÁ Processor V4 Core Wrapper
//
// Wraps Relation Memory Controller around incoming RPC frame.
//
// Input frame:
//   rpc_y, rpc_ra, rpc_rd, rpc_r0, rpc_t
//
// Output frame:
//   out_y, out_ra, out_rd, out_r0, out_t
//
// On HIT:
//   outputs stored frame
//
// On MISS:
//   stores incoming RPC frame and outputs it
//======================================================================

module ifa_v4_core #(
    parameter WIDTH = 8,
    parameter DEPTH = 16
)(
    input  logic                     clk,
    input  logic                     rst,

    input  logic                     rpc_valid,

    input  logic [WIDTH-1:0]         rpc_y,
    input  logic [WIDTH-1:0]         rpc_ra,
    input  logic [WIDTH-1:0]         rpc_rd,
    input  logic [WIDTH-1:0]         rpc_r0,
    input  logic [WIDTH-1:0]         rpc_t,

    output logic                     rmu_hit,
    output logic                     rmu_miss,

    output logic [WIDTH-1:0]         out_y,
    output logic [WIDTH-1:0]         out_ra,
    output logic [WIDTH-1:0]         out_rd,
    output logic [WIDTH-1:0]         out_r0,
    output logic [WIDTH-1:0]         out_t,

    output logic [31:0]              hit_count,
    output logic [31:0]              miss_count,
    output logic [31:0]              store_count,
    output logic [31:0]              evict_count
);

    ifa_relation_memory_controller #(
        .WIDTH(WIDTH),
        .DEPTH(DEPTH)
    ) rmc (
        .clk(clk),
        .rst(rst),

        .req_valid(rpc_valid),

        .in_y(rpc_y),
        .in_ra(rpc_ra),
        .in_rd(rpc_rd),
        .in_r0(rpc_r0),
        .in_t(rpc_t),

        .hit(rmu_hit),
        .miss(rmu_miss),

        .out_y(out_y),
        .out_ra(out_ra),
        .out_rd(out_rd),
        .out_r0(out_r0),
        .out_t(out_t),

        .hit_count(hit_count),
        .miss_count(miss_count),
        .store_count(store_count),
        .evict_count(evict_count)
    );

endmodule

rtl/v4/ifa_rpc_stub.sv
//======================================================================
// IFÁ Processor V4
//
// RPC Stub
//
// Inputs:
//   A, B
//
// Produces Relation Frame:
//   Y  = A + B
//   RA = A & B
//   RD = A ^ B
//   R0 = ~(A | B)
//   T  = RD ^ Y
//
// WIDTH = 8
//======================================================================

module ifa_rpc_stub #(
    parameter WIDTH = 8
)(
    input  logic [WIDTH-1:0] A,
    input  logic [WIDTH-1:0] B,

    output logic [WIDTH-1:0] Y,
    output logic [WIDTH-1:0] RA,
    output logic [WIDTH-1:0] RD,
    output logic [WIDTH-1:0] R0,
    output logic [WIDTH-1:0] T
);

    integer i;

    always_comb begin
        Y  = A + B;
        RA = A & B;
        RD = A ^ B;
        R0 = ~(A | B);
        T  = RD ^ Y;

    end

endmodule

rtl/v4/ifa_v4_end_to_end_core.sv
//======================================================================
// IFÁ Processor V4 End-to-End Core
//
// A,B → RPC Stub → Relation Frame → RMU → Output
//======================================================================

module ifa_v4_end_to_end_core #(
    parameter WIDTH = 8,
    parameter DEPTH = 16
)(
    input  logic                     clk,
    input  logic                     rst,

    input  logic                     in_valid,
    input  logic [WIDTH-1:0]         A,
    input  logic [WIDTH-1:0]         B,

    output logic                     rmu_hit,
    output logic                     rmu_miss,

    output logic [WIDTH-1:0]         out_y,
    output logic [WIDTH-1:0]         out_ra,
    output logic [WIDTH-1:0]         out_rd,
    output logic [WIDTH-1:0]         out_r0,
    output logic [WIDTH-1:0]         out_t,

    output logic [31:0]              hit_count,
    output logic [31:0]              miss_count,
    output logic [31:0]              store_count,
    output logic [31:0]              evict_count
);

    logic [WIDTH-1:0] rpc_y;
    logic [WIDTH-1:0] rpc_ra;
    logic [WIDTH-1:0] rpc_rd;
    logic [WIDTH-1:0] rpc_r0;
    logic [WIDTH-1:0] rpc_t;

    ifa_rpc_stub #(
        .WIDTH(WIDTH)
    ) rpc (
        .A(A),
        .B(B),

        .Y(rpc_y),
        .RA(rpc_ra),
        .RD(rpc_rd),
        .R0(rpc_r0),
        .T(rpc_t)
    );

    ifa_v4_core #(
        .WIDTH(WIDTH),
        .DEPTH(DEPTH)
    ) core (
        .clk(clk),
        .rst(rst),

        .rpc_valid(in_valid),

        .rpc_y(rpc_y),
        .rpc_ra(rpc_ra),
        .rpc_rd(rpc_rd),
        .rpc_r0(rpc_r0),
        .rpc_t(rpc_t),

        .rmu_hit(rmu_hit),
        .rmu_miss(rmu_miss),

        .out_y(out_y),
        .out_ra(out_ra),
        .out_rd(out_rd),
        .out_r0(out_r0),
        .out_t(out_t),

        .hit_count(hit_count),
        .miss_count(miss_count),
        .store_count(store_count),
        .evict_count(evict_count)
    );

endmodule

tb/v4/tb_ifa_v4_modus_tollens.sv
`timescale 1ns/1ps

module tb_ifa_v4_modus_tollens;

    localparam WIDTH = 8;
    localparam DEPTH = 16;

    logic clk;
    logic rst;
    logic in_valid;

    logic [WIDTH-1:0] P;
    logic [WIDTH-1:0] Q;

    logic rmu_hit;
    logic rmu_miss;

    logic [WIDTH-1:0] out_y;
    logic [WIDTH-1:0] out_ra;
    logic [WIDTH-1:0] out_rd;
    logic [WIDTH-1:0] out_r0;
    logic [WIDTH-1:0] out_t;

    logic [31:0] hit_count;
    logic [31:0] miss_count;
    logic [31:0] store_count;
    logic [31:0] evict_count;

    integer cycles;
    logic conclusion_not_p;

    ifa_v4_end_to_end_core #(
        .WIDTH(WIDTH),
        .DEPTH(DEPTH)
    ) dut (
        .clk(clk),
        .rst(rst),

        .in_valid(in_valid),
        .A(P),
        .B(Q),

        .rmu_hit(rmu_hit),
        .rmu_miss(rmu_miss),

        .out_y(out_y),
        .out_ra(out_ra),
        .out_rd(out_rd),
        .out_r0(out_r0),
        .out_t(out_t),

        .hit_count(hit_count),
        .miss_count(miss_count),
        .store_count(store_count),
        .evict_count(evict_count)
    );

    always #5 clk = ~clk;

    always @(posedge clk) begin
        if (!rst)
            cycles <= cycles + 1;
    end

    initial begin
        $dumpfile("sim/v4/ifa_v4_modus_tollens.vcd");
        $dumpvars(0, tb_ifa_v4_modus_tollens);

        clk = 0;
        rst = 1;
        in_valid = 0;
        P = 0;
        Q = 0;
        cycles = 0;
        conclusion_not_p = 0;

        repeat (3) @(posedge clk);
        rst = 0;

        $display("==================================================");
        $display("IFÁ V4 MODUS TOLLENS TEST");
        $display("Rule: P -> Q, observe not-Q, conclude not-P");
        $display("Case: P=1, Q=0");
        $display("==================================================");

        // Send P,Q into relation processor
        @(negedge clk);
        P = 8'h01;
        Q = 8'h00;
        in_valid = 1'b1;

        @(negedge clk);
        in_valid = 1'b0;

        // Wait for output to settle
        @(posedge clk);

        // Ifá relation interpretation:
        // P=1, Q=0 gives active disagreement RD=1.
        // Under implication P->Q, this is the contradiction case.
        if (out_rd == 8'h01 && out_ra == 8'h00) begin
            conclusion_not_p = 1'b1;
        end

        $display("P                    = 0x%02h", P);
        $display("Q                    = 0x%02h", Q);
        $display("Y                    = 0x%02h", out_y);
        $display("RA                   = 0x%02h", out_ra);
        $display("RD                   = 0x%02h", out_rd);
        $display("R0                   = 0x%02h", out_r0);
        $display("T                    = 0x%02h", out_t);
        $display("RMU hit              = %0d", rmu_hit);
        $display("RMU miss             = %0d", rmu_miss);
        $display("conclusion_not_p     = %0d", conclusion_not_p);
        $display("cycles               = %0d", cycles);
        $display("hit_count            = %0d", hit_count);
        $display("miss_count           = %0d", miss_count);

        if (conclusion_not_p !== 1'b1)
            $fatal(1, "Expected modus-tollens conclusion not-P");

        $display("==================================================");
        $display("ALL IFÁ V4 MODUS TOLLENS TESTS PASSED");
        $display("==================================================");

        $finish;
    end

endmodule

sim/v4/ifa_v4_modus_tollens.vcd
$date
	Fri Jul 10 00:18:53 2026
$end
$version
	Icarus Verilog
$end
$timescale
	1ps
$end
$scope module tb_ifa_v4_modus_tollens $end
$var wire 32 ! store_count [31:0] $end
$var wire 1 " rmu_miss $end
$var wire 1 # rmu_hit $end
$var wire 8 $ out_y [7:0] $end
$var wire 8 % out_t [7:0] $end
$var wire 8 & out_rd [7:0] $end
$var wire 8 ' out_ra [7:0] $end
$var wire 8 ( out_r0 [7:0] $end
$var wire 32 ) miss_count [31:0] $end
$var wire 32 * hit_count [31:0] $end
$var wire 32 + evict_count [31:0] $end
$var parameter 32 , DEPTH $end
$var parameter 32 - WIDTH $end
$var reg 8 . P [7:0] $end
$var reg 8 / Q [7:0] $end
$var reg 1 0 clk $end
$var reg 1 1 conclusion_not_p $end
$var reg 1 2 in_valid $end
$var reg 1 3 rst $end
$var integer 32 4 cycles [31:0] $end
$scope module dut $end
$var wire 8 5 A [7:0] $end
$var wire 8 6 B [7:0] $end
$var wire 1 0 clk $end
$var wire 1 2 in_valid $end
$var wire 1 3 rst $end
$var wire 32 7 store_count [31:0] $end
$var wire 8 8 rpc_y [7:0] $end
$var wire 8 9 rpc_t [7:0] $end
$var wire 8 : rpc_rd [7:0] $end
$var wire 8 ; rpc_ra [7:0] $end
$var wire 8 < rpc_r0 [7:0] $end
$var wire 1 " rmu_miss $end
$var wire 1 # rmu_hit $end
$var wire 8 = out_y [7:0] $end
$var wire 8 > out_t [7:0] $end
$var wire 8 ? out_rd [7:0] $end
$var wire 8 @ out_ra [7:0] $end
$var wire 8 A out_r0 [7:0] $end
$var wire 32 B miss_count [31:0] $end
$var wire 32 C hit_count [31:0] $end
$var wire 32 D evict_count [31:0] $end
$var parameter 32 E DEPTH $end
$var parameter 32 F WIDTH $end
$scope module core $end
$var wire 1 0 clk $end
$var wire 1 2 rpc_valid $end
$var wire 1 3 rst $end
$var wire 32 G store_count [31:0] $end
$var wire 8 H rpc_y [7:0] $end
$var wire 8 I rpc_t [7:0] $end
$var wire 8 J rpc_rd [7:0] $end
$var wire 8 K rpc_ra [7:0] $end
$var wire 8 L rpc_r0 [7:0] $end
$var wire 1 " rmu_miss $end
$var wire 1 # rmu_hit $end
$var wire 8 M out_y [7:0] $end
$var wire 8 N out_t [7:0] $end
$var wire 8 O out_rd [7:0] $end
$var wire 8 P out_ra [7:0] $end
$var wire 8 Q out_r0 [7:0] $end
$var wire 32 R miss_count [31:0] $end
$var wire 32 S hit_count [31:0] $end
$var wire 32 T evict_count [31:0] $end
$var parameter 32 U DEPTH $end
$var parameter 32 V WIDTH $end
$scope module rmc $end
$var wire 1 0 clk $end
$var wire 1 2 req_valid $end
$var wire 1 3 rst $end
$var wire 8 W in_y [7:0] $end
$var wire 8 X in_t [7:0] $end
$var wire 8 Y in_rd [7:0] $end
$var wire 8 Z in_ra [7:0] $end
$var wire 8 [ in_r0 [7:0] $end
$var parameter 32 \ DEPTH $end
$var parameter 32 ] INDEX_W $end
$var parameter 32 ^ WIDTH $end
$var reg 32 _ evict_count [31:0] $end
$var reg 4 ` fifo_ptr [3:0] $end
$var reg 1 # hit $end
$var reg 32 a hit_count [31:0] $end
$var reg 1 b lookup_hit $end
$var reg 4 c lookup_index [3:0] $end
$var reg 1 " miss $end
$var reg 32 d miss_count [31:0] $end
$var reg 8 e out_r0 [7:0] $end
$var reg 8 f out_ra [7:0] $end
$var reg 8 g out_rd [7:0] $end
$var reg 8 h out_t [7:0] $end
$var reg 8 i out_y [7:0] $end
$var reg 32 j store_count [31:0] $end
$var integer 32 k i [31:0] $end
$scope begin $ivl_for_loop0 $end
$var integer 32 l j [31:0] $end
$upscope $end
$upscope $end
$upscope $end
$scope module rpc $end
$var wire 8 m A [7:0] $end
$var wire 8 n B [7:0] $end
$var parameter 32 o WIDTH $end
$var reg 8 p R0 [7:0] $end
$var reg 8 q RA [7:0] $end
$var reg 8 r RD [7:0] $end
$var reg 8 s T [7:0] $end
$var reg 8 t Y [7:0] $end
$upscope $end
$upscope $end
$upscope $end
$enddefinitions $end
$comment Show the parameter values. $end
$dumpall
b1000 o
b1000 ^
b100 ]
b10000 \
b1000 V
b10000 U
b1000 F
b10000 E
b1000 -
b10000 ,
$end
#0
$dumpvars
b0 t
b0 s
b0 r
b0 q
b11111111 p
b0 n
b0 m
b10000 l
bx k
bx j
bx i
bx h
bx g
bx f
bx e
bx d
b0 c
0b
bx a
bx `
bx _
b11111111 [
b0 Z
b0 Y
b0 X
b0 W
bx T
bx S
bx R
bx Q
bx P
bx O
bx N
bx M
b11111111 L
b0 K
b0 J
b0 I
b0 H
bx G
bx D
bx C
bx B
bx A
bx @
bx ?
bx >
bx =
b11111111 <
b0 ;
b0 :
b0 9
b0 8
bx 7
b0 6
b0 5
b0 4
13
02
01
00
b0 /
b0 .
bx +
bx *
bx )
bx (
bx '
bx &
bx %
bx $
x#
x"
bx !
$end
#5000
b10000 l
b0 +
b0 D
b0 T
b0 _
b0 !
b0 7
b0 G
b0 j
b0 )
b0 B
b0 R
b0 d
b0 *
b0 C
b0 S
b0 a
b0 %
b0 >
b0 N
b0 h
b0 (
b0 A
b0 Q
b0 e
b0 &
b0 ?
b0 O
b0 g
b0 '
b0 @
b0 P
b0 f
b0 $
b0 =
b0 M
b0 i
0"
0#
b0 `
b10000 k
10
#10000
00
#15000
b10000 k
10
#20000
00
#25000
b1 4
03
10
#30000
b10000 l
b11111110 <
b11111110 L
b11111110 [
b11111110 p
b1 :
b1 J
b1 Y
b1 r
b1 8
b1 H
b1 W
b1 t
12
b1 .
b1 5
b1 m
00
#35000
1b
b10000 l
b10 4
b1 `
b11111110 (
b11111110 A
b11111110 Q
b11111110 e
b1 &
b1 ?
b1 O
b1 g
b1 $
b1 =
b1 M
b1 i
b1 !
b1 7
b1 G
b1 j
b1 )
b1 B
b1 R
b1 d
1"
10
#40000
02
00
#45000
0"
b11 4
11
10
